inspec_ai/__init__.py
inspec_ai/config.py
inspec_ai/analytics/__init__.py
inspec_ai/analytics/telemetry_service.py
inspec_ai/metrics/__init__.py
inspec_ai/metrics/mase.py
inspec_ai/preprocessing/__init__.py
inspec_ai/preprocessing/category_cleaner.py
inspec_ai/preprocessing/missing_values.py
inspec_ai/preprocessing/predictive_features.py
inspec_ai/preprocessing/time_enhancement.py
inspec_ai/quality/__init__.py
inspec_ai/quality/constants.py
inspec_ai/quality/enums.py
inspec_ai/quality/evaluate_quality_standards.py
inspec_ai/quality/exceptions.py
inspec_ai/quality/quality_standard.py
inspec_ai/quality/utils.py
inspec_ai/quality/visualisation/__init__.py
inspec_ai/quality/visualisation/visualisation.py
inspec_ai/quality/visualisation/assets/styles.css
inspec_ai/quality/visualisation/assets/fonts/nunito-v23-latin/nunito-v23-latin-regular.eot
inspec_ai/quality/visualisation/assets/fonts/nunito-v23-latin/nunito-v23-latin-regular.svg
inspec_ai/quality/visualisation/assets/fonts/nunito-v23-latin/nunito-v23-latin-regular.ttf
inspec_ai/quality/visualisation/assets/fonts/nunito-v23-latin/nunito-v23-latin-regular.woff
inspec_ai/quality/visualisation/assets/fonts/nunito-v23-latin/nunito-v23-latin-regular.woff2
inspec_ai/quality/visualisation/assets/icons/exclamation_point.png
inspec_ai/quality/visualisation/assets/icons/green_check.png
inspec_ai/quality/visualisation/assets/icons/red_cross.png
inspec_ai/quality/visualisation/templates/main_report.html
inspec_ai/utils/__init__.py
inspec_ai/utils/text_utils.py
inspec_ai/utils/utils.py
inspec_ai/weather/__init__.py
inspec_ai/weather/weather.py
inspec_ai-0.1.15.data/data/inspec_ai/exclamation_point.png
inspec_ai-0.1.15.data/data/inspec_ai/green_check.png
inspec_ai-0.1.15.data/data/inspec_ai/main_report.html
inspec_ai-0.1.15.data/data/inspec_ai/nunito-v23-latin-regular.eot
inspec_ai-0.1.15.data/data/inspec_ai/nunito-v23-latin-regular.svg
inspec_ai-0.1.15.data/data/inspec_ai/nunito-v23-latin-regular.ttf
inspec_ai-0.1.15.dist-info/LICENSE.md
inspec_ai-0.1.15.dist-info/METADATA
inspec_ai-0.1.15.dist-info/WHEEL
inspec_ai-0.1.15.dist-info/top_level.txt
inspec_ai-0.1.15.dist-info/RECORD
