Metadata-Version: 2.1
Name: inspec-ai
Version: 0.1.15
Summary: Library containing all the prototypes that were developped by the Moov AI product team.
Home-page: https://moov.ai/en/
Author: MoovAI Technologies Inc
Author-email: info@moov.ai
License: Internal Use
Platform: UNKNOWN
Classifier: Development Status :: 3 - Alpha
Classifier: Programming Language :: Python :: 3
Classifier: Programming Language :: Python :: 3.7
Classifier: Programming Language :: Python :: 3.8
Classifier: Programming Language :: Python :: 3.9
License-File: LICENSE.md
Requires-Dist: colorama (==0.4.4)
Requires-Dist: holidays (==0.12)
Requires-Dist: jinja2 (==3.0.3)
Requires-Dist: kaggle (==1.5.12)
Requires-Dist: matplotlib (==3.5.1)
Requires-Dist: numpy (==1.21.3)
Requires-Dist: pandas (==1.3.4)
Requires-Dist: pandas-profiling (==3.1.0)
Requires-Dist: pillow (==9.1.0)
Requires-Dist: scikit-learn (==1.0.2)
Requires-Dist: fuzzywuzzy (==0.18.0)
Requires-Dist: requests (==2.28.1)
